LICENSE
MANIFEST.in
README.md
requirements.txt
setup.py
blackbirds/__init__.py
blackbirds/jacfwd.py
blackbirds/losses.py
blackbirds/mpi_setup.py
blackbirds/posterior_estimators.py
blackbirds/simulate.py
blackbirds/utils.py
blackbirds.egg-info/PKG-INFO
blackbirds.egg-info/SOURCES.txt
blackbirds.egg-info/dependency_links.txt
blackbirds.egg-info/requires.txt
blackbirds.egg-info/top_level.txt
blackbirds/infer/__init__.py
blackbirds/infer/mcmc.py
blackbirds/infer/smd.py
blackbirds/infer/vi.py
blackbirds/models/__init__.py
blackbirds/models/brock_hommes.py
blackbirds/models/june.py
blackbirds/models/model.py
blackbirds/models/normal.py
blackbirds/models/rama_cont.py
blackbirds/models/random_walk.py
blackbirds/models/sir.py
blackbirds/models/stochastic_volatility.py
test/test_jacfwd.py
test/test_losses.py
test/test_posterior_estimators.py
test/test_simulate.py
test/test_utils.py