Metadata-Version: 2.1
Name: blackbirds
Version: 1.0.0
Summary: Black-Box Inference foR Differentiable Simulators.
Home-page: https://github.com/arnauqb/blackbirds
Author: Ayush Chopra and Joel Dyer and Arnau Quera-Bofarull
Author-email: arnauq@protonmail.com
License: MIT License
License-File: LICENSE
